quantized_mesh_tile/__init__.py
quantized_mesh_tile/bbsphere.py
quantized_mesh_tile/cartesian3d.py
quantized_mesh_tile/global_geodetic.py
quantized_mesh_tile/horizon_occlusion_point.py
quantized_mesh_tile/llh_ecef.py
quantized_mesh_tile/terrain.py
quantized_mesh_tile/topology.py
quantized_mesh_tile/utils.py
quantized_mesh_tile-0.6.1.dist-info/LICENSE.txt
quantized_mesh_tile-0.6.1.dist-info/METADATA
quantized_mesh_tile-0.6.1.dist-info/WHEEL
quantized_mesh_tile-0.6.1.dist-info/top_level.txt
quantized_mesh_tile-0.6.1.dist-info/RECORD
